<?xml version="1.0" encoding="UTF-8"?>

<roster id="skaven.roster">

<!--
LRB 4.0

0-12 Linemen        50,000 7 3 3 7 None
0-2  Throwers       70,000 7 3 3 7 Sure Hands, Pass
0-4  Gutter Runners 80,000 9 2 4 7 Dodge
0-2  Storm Vermin   90,000 7 3 3 8 Block

Re-roll counter: 60,000 gold pieces each
-->

  <name>Skaven</name>
  <type>Regular</type>
  <reroll_cost>60000</reroll_cost>	
  <max_rerolls>8</max_rerolls>	

  <position id="skaven.lineman">
  	<quantity>12</quantity>
  	<name>Skaven Lineman</name>
  	<type>Regular</type>
  	<cost>50000</cost>
    <movement>7</movement>
    <strength>3</strength>
    <agility>3</agility>
    <armour>7</armour>
    <icon-list>
      <portrait>players/skaven/skLineman.gif</portrait>
      <home standing="players/skaven/sklineman1.gif" moving="players/skaven/sklineman1an.gif" />
      <away standing="players/skaven/sklineman1b.gif" moving="players/skaven/sklineman1ban.gif" />
      <home standing="players/skaven/sklineman2.gif" moving="players/skaven/sklineman2an.gif" />
      <away standing="players/skaven/sklineman2b.gif" moving="players/skaven/sklineman2ban.gif" />
      <home standing="players/skaven/sklineman3.gif" moving="players/skaven/sklineman3an.gif" />
      <away standing="players/skaven/sklineman3b.gif" moving="players/skaven/sklineman3ban.gif" />
    </icon-list>
  	<skill-list />
  	<skillcategory-list>
      <normal>General Skill</normal>
      <double>General Trait</double>
      <double>Strength Skill</double>
      <double>Agility Skill</double>
      <double>Passing Skill</double>
      <double>Physical Trait</double>
  	</skillcategory-list>
  </position>

  <position id="skaven.thrower">
  	<quantity>2</quantity>
  	<name>Skaven Thrower</name>
  	<type>Regular</type>
  	<cost>70000</cost>
    <movement>7</movement>
    <strength>3</strength>
    <agility>3</agility>
    <armour>7</armour>
    <icon-list>
      <portrait>players/skaven/skThrower.gif</portrait>
      <home standing="players/skaven/skthrower1.gif" moving="players/skaven/skthrower1an.gif" />
      <away standing="players/skaven/skthrower1b.gif" moving="players/skaven/skthrower1ban.gif" />
    </icon-list>
  	<skill-list>
  	  <skill>Pass</skill>
  	  <skill>Sure Hands</skill>
  	</skill-list>
  	<skillcategory-list>
      <normal>General Skill</normal>
      <normal>Passing Skill</normal>
      <double>General Trait</double>
      <double>Passing Trait</double>
      <double>Strength Skill</double>
      <double>Agility Skill</double>
      <double>Physical Trait</double>
  	</skillcategory-list>
  </position>

  <position id="skaven.stormvermin">
  	<quantity>2</quantity>
  	<name>Skaven Storm Vermin</name>
  	<type>Regular</type>
  	<cost>90000</cost>
    <movement>7</movement>
    <strength>3</strength>
    <agility>3</agility>
    <armour>8</armour>
    <icon-list>
      <portrait>players/skaven/skStorm.gif</portrait>
      <home standing="players/skaven/skstorm1.gif" moving="players/skaven/skstorm1an.gif" />
      <away standing="players/skaven/skstorm1b.gif" moving="players/skaven/skstorm1ban.gif" />
      <home standing="players/skaven/skstorm2.gif" moving="players/skaven/skstorm2an.gif" />
      <away standing="players/skaven/skstorm2b.gif" moving="players/skaven/skstorm2ban.gif" />
    </icon-list>
  	<skill-list>
  	  <skill>Block</skill>
  	</skill-list>
  	<skillcategory-list>
      <normal>General Skill</normal>
      <normal>Strength Skill</normal>
      <double>General Trait</double>
      <double>Strength Trait</double>
      <double>Passing Skill</double>
      <double>Agility Skill</double>
      <double>Physical Trait</double>
  	</skillcategory-list>
  </position>

  <position id="skaven.gutterrunner">
  	<quantity>4</quantity>
  	<name>Skaven Gutter Runner</name>
  	<type>Regular</type>
  	<cost>80000</cost>
    <movement>9</movement>
    <strength>2</strength>
    <agility>4</agility>
    <armour>7</armour>
    <icon-list>
      <portrait>players/skaven/skGutter.gif</portrait>
      <home standing="players/skaven/skrunner1.gif" moving="players/skaven/skrunner1an.gif" />
      <away standing="players/skaven/skrunner1b.gif" moving="players/skaven/skrunner1ban.gif" />
      <home standing="players/skaven/skrunner2.gif" moving="players/skaven/skrunner2an.gif" />
      <away standing="players/skaven/skrunner2b.gif" moving="players/skaven/skrunner2ban.gif" />
    </icon-list>
  	<skill-list>
  	  <skill>Dodge</skill>
  	</skill-list>
  	<skillcategory-list>
      <normal>General Skill</normal>
      <normal>Agility Skill</normal>
      <double>General Trait</double>
      <double>Agility Trait</double>
      <double>Passing Skill</double>
      <double>Strength Skill</double>
      <double>Physical Trait</double>
  	</skillcategory-list>
  </position>

</roster>
